NeuroVisKit/__init__.py
NeuroVisKit/minimal.py
NeuroVisKit/setup.py
NeuroVisKit/_utils/__init__.py
NeuroVisKit/_utils/io.py
NeuroVisKit/_utils/lightning.py
NeuroVisKit/_utils/logging.py
NeuroVisKit/_utils/mess.py
NeuroVisKit/_utils/postprocess.py
NeuroVisKit/_utils/regularization.py
NeuroVisKit/_utils/utils.py
NeuroVisKit/tests/regularization_scaling_test.py
NeuroVisKit/tests/test_regularization.py
NeuroVisKit/tests/tests.py
NeuroVisKit/utils/__init__.py
NeuroVisKit/utils/datasets.py
NeuroVisKit/utils/evaluate.py
NeuroVisKit/utils/lightning.py
NeuroVisKit/utils/loss.py
NeuroVisKit/utils/mei.py
NeuroVisKit/utils/models.py
NeuroVisKit/utils/plotting.py
NeuroVisKit/utils/postprocess.py
NeuroVisKit/utils/regularization.py
NeuroVisKit/utils/rf.py
NeuroVisKit/utils/toy_datasets.py
NeuroVisKit/utils/utils.py
NeuroVisKit-0.0.2.dist-info/LICENSE
NeuroVisKit-0.0.2.dist-info/METADATA
NeuroVisKit-0.0.2.dist-info/WHEEL
NeuroVisKit-0.0.2.dist-info/top_level.txt
NeuroVisKit-0.0.2.dist-info/RECORD
